ivtmetrics/__init__.py
ivtmetrics/detection.py
ivtmetrics/disentangle.py
ivtmetrics/maps.txt
ivtmetrics/recognition.py
ivtmetrics-0.1.5.dist-info/LICENSE
ivtmetrics-0.1.5.dist-info/METADATA
ivtmetrics-0.1.5.dist-info/WHEEL
ivtmetrics-0.1.5.dist-info/top_level.txt
ivtmetrics-0.1.5.dist-info/RECORD
