Metadata-Version: 2.1
Name: ivtmetrics
Version: 0.1.5
Summary: A Python evaluation metrics package for action triplet recognition
Home-page: https://github.com/CAMMA-public/ivtmetrics
Download-URL: https://github.com/CAMMA-public/ivtmetrics/archive/refs/tags/v0.1.5.tar.gz
Author: Chinedu Nwoye
Author-email: nwoye.chinedu@gmail.com
License: BSD 2-clause
Keywords: triplet,average precision,AP,mAP
Classifier: Development Status :: 1 - Planning
Classifier: Intended Audience :: Science/Research
Classifier: License :: OSI Approved :: BSD License
Classifier: Topic :: Software Development :: Build Tools
Classifier: Programming Language :: Python :: 3
Classifier: Programming Language :: Python :: 3.4
Classifier: Programming Language :: Python :: 3.5
Classifier: Programming Language :: Python :: 3.6
Classifier: Programming Language :: Python :: 3.7
Classifier: Programming Language :: Python :: 3.8
Classifier: Programming Language :: Python :: 3.9
License-File: LICENSE
Requires-Dist: scikit-learn>=1.0.2
Requires-Dist: numpy>=1.21
